csttodate/__init__.py
csttodate/csttodate.py
csttodate-0.0.1.dist-info/METADATA
csttodate-0.0.1.dist-info/WHEEL
csttodate-0.0.1.dist-info/top_level.txt
csttodate-0.0.1.dist-info/RECORD
